{
  "m_GameObject": {
    "m_FileID": 0,
    "m_PathID": 0
  },
  "m_Enabled": 1,
  "m_Script": {
    "m_FileID": 1,
    "m_PathID": -4966018532029360186
  },
  "m_Name": "A06006.book",
  "importVersion": 0,
  "importGridList": [
    {
      "rows": [
        {
          "rowIndex": 0,
          "strings": [
            "Command",
            "Arg1",
            "Arg2",
            "Arg3",
            "Arg4",
            "Arg5",
            "Arg6",
            "Arg7",
            "Arg8",
            "WaitType",
            "Text",
            "PageCtrl",
            "WindowType",
            "Voice",
            "Voice1",
            "Voice_JP",
            "Voice1_JP",
            "Voice_EN",
            "Voice1_EN"
          ],
          "isEmpty": 0,
          "isCommentOut": 0
        },
        {
          "rowIndex": 1,
          "strings": [
            "ChangeMessageWindow",
            "AVGWindow",
            "",
            "",
            "",
            "",
            "",
            "",
            "",
            "",
            "",
            "",
            "",
            "",
            "",
            "",
            "",
            "",
            ""
          ],
          "isEmpty": 0,
          "isCommentOut": 0
        },
        {
          "rowIndex": 2,
          "strings": [
            "Character",
            "莱娜日常装",
            "Idle,0|Smile,2",
            "中",
            "",
            "",
            ".5",
            "1"
          ],
          "isEmpty": 0,
          "isCommentOut": 0
        },
        {
          "rowIndex": 3,
          "strings": [
            "Bg",
            "BG_None_Black_01",
            "",
            "BgDefault",
            "",
            "",
            ".2",
            "0",
            "",
            "",
            "",
            "",
            "",
            "",
            "",
            "",
            "",
            "",
            ""
          ],
          "isEmpty": 0,
          "isCommentOut": 0
        },
        {
          "rowIndex": 4,
          "strings": [
            "Bg",
            "BG_None_Class_02",
            "",
            "BgDefault",
            "",
            "",
            "3",
            "0",
            "EaseInSine",
            "",
            "",
            "",
            "",
            "",
            "",
            "",
            "",
            "",
            ""
          ],
          "isEmpty": 0,
          "isCommentOut": 0
        },
        {
          "rowIndex": 5,
          "strings": [
            "Bgm",
            "黄区自然",
            "",
            "1",
            "",
            "0",
            "3",
            "",
            "",
            "",
            "",
            "",
            "",
            "",
            "",
            "",
            "",
            "",
            ""
          ],
          "isEmpty": 0,
          "isCommentOut": 0
        },
        {
          "rowIndex": 6,
          "strings": [
            "Se",
            "2010039",
            "TRUE",
            "1",
            "",
            "0",
            "3",
            "",
            "",
            "",
            "",
            "",
            "",
            "",
            "",
            "",
            "",
            "",
            ""
          ],
          "isEmpty": 0,
          "isCommentOut": 0
        },
        {
          "rowIndex": 7,
          "strings": [
            "Se",
            "2010073",
            "",
            "1",
            "",
            "2",
            "0",
            "",
            "",
            "",
            "",
            "",
            "",
            "",
            "",
            "",
            "",
            "",
            ""
          ],
          "isEmpty": 0,
          "isCommentOut": 0
        },
        {
          "rowIndex": 8,
          "strings": [
            "Text",
            "62",
            "莱娜日常装",
            "",
            "",
            "",
            "",
            "2",
            "",
            "",
            "206006001"
          ],
          "isEmpty": 0,
          "isCommentOut": 0
        },
        {
          "rowIndex": 9,
          "strings": [
            "Text",
            "62",
            "莱娜日常装",
            "",
            "",
            "",
            "",
            "",
            "",
            "",
            "206006002"
          ],
          "isEmpty": 0,
          "isCommentOut": 0
        },
        {
          "rowIndex": 10,
          "strings": [
            "Character",
            "莱娜日常装",
            "Idle,0.5",
            "中"
          ],
          "isEmpty": 0,
          "isCommentOut": 0
        },
        {
          "rowIndex": 11,
          "strings": [
            "Text",
            "62",
            "莱娜日常装",
            "",
            "",
            "",
            "",
            "",
            "",
            "",
            "206006003"
          ],
          "isEmpty": 0,
          "isCommentOut": 0
        },
        {
          "rowIndex": 12,
          "strings": [
            "Text",
            "50",
            "",
            "",
            "",
            "",
            "",
            "",
            "",
            "",
            "206006004"
          ],
          "isEmpty": 0,
          "isCommentOut": 0
        },
        {
          "rowIndex": 13,
          "strings": [
            "Character",
            "莱娜日常装",
            "Smile,0.5",
            "中"
          ],
          "isEmpty": 0,
          "isCommentOut": 0
        },
        {
          "rowIndex": 14,
          "strings": [
            "Text",
            "62",
            "莱娜日常装",
            "",
            "",
            "",
            "",
            "",
            "",
            "",
            "206006005"
          ],
          "isEmpty": 0,
          "isCommentOut": 0
        },
        {
          "rowIndex": 15,
          "strings": [
            "Text",
            "65",
            "",
            "",
            "",
            "",
            "",
            "",
            "",
            "",
            "206006006"
          ],
          "isEmpty": 0,
          "isCommentOut": 0
        },
        {
          "rowIndex": 16,
          "strings": [
            "Character",
            "莱娜日常装",
            "Dissatisfied,0.5",
            "中"
          ],
          "isEmpty": 0,
          "isCommentOut": 0
        },
        {
          "rowIndex": 17,
          "strings": [
            "Text",
            "62",
            "莱娜日常装",
            "",
            "",
            "",
            "",
            "",
            "",
            "",
            "206006007"
          ],
          "isEmpty": 0,
          "isCommentOut": 0
        },
        {
          "rowIndex": 18,
          "strings": [
            "Text",
            "65",
            "",
            "",
            "",
            "",
            "",
            "",
            "",
            "",
            "206006008"
          ],
          "isEmpty": 0,
          "isCommentOut": 0
        },
        {
          "rowIndex": 19,
          "strings": [
            "Text",
            "50",
            "",
            "",
            "",
            "",
            "",
            "",
            "",
            "",
            "206006009"
          ],
          "isEmpty": 0,
          "isCommentOut": 0
        },
        {
          "rowIndex": 20,
          "strings": [
            "Character",
            "莱娜日常装",
            "Panic,0.5",
            "中"
          ],
          "isEmpty": 0,
          "isCommentOut": 0
        },
        {
          "rowIndex": 21,
          "strings": [
            "StopBgm",
            "黄区自然",
            "",
            "",
            "",
            "",
            "2",
            "0",
            "",
            "",
            "",
            "",
            "",
            "",
            "",
            "",
            "",
            "",
            ""
          ],
          "isEmpty": 0,
          "isCommentOut": 0
        },
        {
          "rowIndex": 22,
          "strings": [
            "Se",
            "2010086",
            "TRUE",
            "1",
            "",
            "0",
            "3",
            "",
            "",
            "",
            "",
            "",
            "",
            "",
            "",
            "",
            "",
            "",
            ""
          ],
          "isEmpty": 0,
          "isCommentOut": 0
        },
        {
          "rowIndex": 23,
          "strings": [
            "Text",
            "65",
            "",
            "",
            "",
            "",
            "",
            "",
            "",
            "",
            "206006010"
          ],
          "isEmpty": 0,
          "isCommentOut": 0
        },
        {
          "rowIndex": 24,
          "strings": [
            "Character",
            "莱娜日常装",
            "Think,0.5",
            "中"
          ],
          "isEmpty": 0,
          "isCommentOut": 0
        },
        {
          "rowIndex": 25,
          "strings": [
            "Text",
            "50",
            "",
            "",
            "",
            "",
            "",
            "",
            "",
            "",
            "206006011"
          ],
          "isEmpty": 0,
          "isCommentOut": 0
        },
        {
          "rowIndex": 26,
          "strings": [
            "Character",
            "莱娜日常装",
            "Idle,1.5",
            "中"
          ],
          "isEmpty": 0,
          "isCommentOut": 0
        },
        {
          "rowIndex": 27,
          "strings": [
            "CharacterOff",
            "莱娜日常装",
            "",
            "",
            "",
            "",
            "2",
            "4",
            "",
            "",
            "",
            "",
            "",
            "",
            "",
            "",
            "",
            "",
            ""
          ],
          "isEmpty": 0,
          "isCommentOut": 0
        },
        {
          "rowIndex": 28,
          "strings": [
            "BgOff",
            "BgCGBackGround",
            "",
            "",
            "",
            "",
            "",
            "",
            "",
            "",
            "",
            "",
            "",
            "",
            "",
            "",
            "",
            "",
            ""
          ],
          "isEmpty": 0,
          "isCommentOut": 0
        },
        {
          "rowIndex": 29,
          "strings": [
            "BgOff",
            "BG_None_Class_02",
            "",
            "",
            "",
            "",
            "2",
            "5",
            "",
            "",
            "",
            "",
            "",
            "",
            "",
            "",
            "",
            "",
            ""
          ],
          "isEmpty": 0,
          "isCommentOut": 0
        },
        {
          "rowIndex": 30,
          "strings": [
            "StopSe",
            "2010039",
            "",
            "",
            "",
            "",
            "2",
            "5",
            "",
            "",
            "",
            "",
            "",
            "",
            "",
            "",
            "",
            "",
            ""
          ],
          "isEmpty": 0,
          "isCommentOut": 0
        },
        {
          "rowIndex": 31,
          "strings": [
            "StopSe",
            "2010086",
            "",
            "",
            "",
            "",
            "2",
            "5",
            "",
            "",
            "",
            "",
            "",
            "",
            "",
            "",
            "",
            "",
            ""
          ],
          "isEmpty": 0,
          "isCommentOut": 0
        },
        {
          "rowIndex": 32,
          "strings": [
            "Text",
            "62",
            "莱娜日常装",
            "",
            "",
            "",
            "Next",
            "",
            "",
            "",
            "206006012"
          ],
          "isEmpty": 0,
          "isCommentOut": 0
        },
        {
          "rowIndex": 33,
          "strings": [
            "EndScenario"
          ],
          "isEmpty": 0,
          "isCommentOut": 0
        }
      ],
      "name": "Assets/Utage/BuildResources/Activity/ChapterActivity06/A06006.xls:A06006",
      "type": 1,
      "textLength": 776,
      "headerRow": 0,
      "entityIndexTbl": [],
      "entityDataList": []
    }
  ]
}