{
  "m_GameObject": {
    "m_FileID": 0,
    "m_PathID": 0
  },
  "m_Enabled": 1,
  "m_Script": {
    "m_FileID": 1,
    "m_PathID": -4966018532029360186
  },
  "m_Name": "T04506.book",
  "importVersion": 0,
  "importGridList": [
    {
      "rows": [
        {
          "rowIndex": 0,
          "strings": [
            "Command",
            "Arg1",
            "Arg2",
            "Arg3",
            "Arg4",
            "Arg5",
            "Arg6",
            "Arg7",
            "Arg8",
            "WaitType",
            "Text",
            "PageCtrl",
            "WindowType",
            "Voice",
            "Voice1",
            "Voice_JP",
            "Voice1_JP",
            "Voice_EN",
            "Voice1_EN"
          ],
          "isEmpty": 0,
          "isCommentOut": 0
        },
        {
          "rowIndex": 1,
          "strings": [
            "ChangeMessageWindow",
            "AVGNarrator",
            "",
            "",
            "",
            "",
            "",
            "",
            "",
            "",
            "",
            "",
            "",
            "",
            "",
            "",
            "",
            "",
            ""
          ],
          "isEmpty": 0,
          "isCommentOut": 0
        },
        {
          "rowIndex": 2,
          "strings": [
            "Bg",
            "BG_None_Black_01",
            "",
            "BgDefault",
            "",
            "",
            "0.2",
            "0",
            "Linear",
            "",
            "",
            "",
            "",
            "",
            "",
            "",
            "",
            "",
            ""
          ],
          "isEmpty": 0,
          "isCommentOut": 0
        },
        {
          "rowIndex": 3,
          "strings": [
            "Bg",
            "BG_Green_404Corridor_Day_01",
            "",
            "BgDefault",
            "",
            "",
            "2",
            "0",
            "EaseInSine",
            "",
            "",
            "",
            "",
            "",
            "",
            "",
            "",
            "",
            ""
          ],
          "isEmpty": 0,
          "isCommentOut": 0
        },
        {
          "rowIndex": 4,
          "strings": [
            "Bgm",
            "暧昧抒情",
            "",
            "1",
            "",
            "0",
            "2",
            "",
            "",
            "",
            "",
            "",
            "",
            "",
            "",
            "",
            "",
            "",
            ""
          ],
          "isEmpty": 0,
          "isCommentOut": 0
        },
        {
          "rowIndex": 5,
          "strings": [
            "Se",
            "2010047",
            "True",
            "1",
            "",
            "0",
            "2",
            "",
            "",
            "",
            "",
            "",
            "",
            "",
            "",
            "",
            "",
            "",
            ""
          ],
          "isEmpty": 0,
          "isCommentOut": 0
        },
        {
          "rowIndex": 6,
          "strings": [
            "Text",
            "",
            "",
            "",
            "",
            "",
            "",
            "",
            "",
            "",
            "504506001"
          ],
          "isEmpty": 0,
          "isCommentOut": 0
        },
        {
          "rowIndex": 7,
          "strings": [
            "ChangeMessageWindow",
            "AVGWindow",
            "",
            "",
            "",
            "",
            "",
            "",
            "",
            "",
            "",
            "",
            "",
            "",
            "",
            "",
            "",
            "",
            ""
          ],
          "isEmpty": 0,
          "isCommentOut": 0
        },
        {
          "rowIndex": 8,
          "strings": [
            "Character",
            "洛贝拉SSR",
            "Think,0",
            "中",
            "",
            "",
            "0.5",
            "0.5"
          ],
          "isEmpty": 0,
          "isCommentOut": 0
        },
        {
          "rowIndex": 9,
          "strings": [
            "Text",
            "426",
            "洛贝拉SSR",
            "",
            "",
            "",
            "",
            "1.5",
            "",
            "",
            "504506002"
          ],
          "isEmpty": 0,
          "isCommentOut": 0
        },
        {
          "rowIndex": 10,
          "strings": [
            "ChangeMessageWindow",
            "AVGNarrator",
            "",
            "",
            "",
            "",
            "",
            "",
            "",
            "",
            "",
            "",
            "",
            "",
            "",
            "",
            "",
            "",
            ""
          ],
          "isEmpty": 0,
          "isCommentOut": 0
        },
        {
          "rowIndex": 11,
          "strings": [
            "Character",
            "洛贝拉SSR",
            "Think,0",
            "中"
          ],
          "isEmpty": 0,
          "isCommentOut": 0
        },
        {
          "rowIndex": 12,
          "strings": [
            "Se",
            "2010158",
            "False",
            "1",
            "",
            "0",
            "0",
            "",
            "",
            "",
            "",
            "",
            "",
            "",
            "",
            "",
            "",
            "",
            ""
          ],
          "isEmpty": 0,
          "isCommentOut": 0
        },
        {
          "rowIndex": 13,
          "strings": [
            "Se",
            "20110028",
            "False",
            "1",
            "",
            "1",
            "0",
            "",
            "",
            "",
            "",
            "",
            "",
            "",
            "",
            "",
            "",
            "",
            ""
          ],
          "isEmpty": 0,
          "isCommentOut": 0
        },
        {
          "rowIndex": 14,
          "strings": [
            "Text",
            "",
            "",
            "",
            "",
            "",
            "",
            "",
            "",
            "",
            "504506003"
          ],
          "isEmpty": 0,
          "isCommentOut": 0
        },
        {
          "rowIndex": 15,
          "strings": [
            "ChangeMessageWindow",
            "AVGWindow",
            "",
            "",
            "",
            "",
            "",
            "",
            "",
            "",
            "",
            "",
            "",
            "",
            "",
            "",
            "",
            "",
            ""
          ],
          "isEmpty": 0,
          "isCommentOut": 0
        },
        {
          "rowIndex": 16,
          "strings": [
            "Character",
            "洛贝拉SSR",
            "Think,0|Surprised,0.5",
            "中"
          ],
          "isEmpty": 0,
          "isCommentOut": 0
        },
        {
          "rowIndex": 17,
          "strings": [
            "Text",
            "50",
            "",
            "",
            "",
            "",
            "",
            "",
            "",
            "",
            "504506004"
          ],
          "isEmpty": 0,
          "isCommentOut": 0
        },
        {
          "rowIndex": 18,
          "strings": [
            "Character",
            "洛贝拉SSR",
            "Surprised,0",
            "中"
          ],
          "isEmpty": 0,
          "isCommentOut": 0
        },
        {
          "rowIndex": 19,
          "strings": [
            "Text",
            "426",
            "洛贝拉SSR",
            "",
            "",
            "",
            "",
            "",
            "",
            "",
            "504506005"
          ],
          "isEmpty": 0,
          "isCommentOut": 0
        },
        {
          "rowIndex": 20,
          "strings": [
            "Character",
            "洛贝拉SSR",
            "Surprised,0|Tender,0.5",
            "中"
          ],
          "isEmpty": 0,
          "isCommentOut": 0
        },
        {
          "rowIndex": 21,
          "strings": [
            "Text",
            "426",
            "洛贝拉SSR",
            "",
            "",
            "",
            "",
            "",
            "",
            "",
            "504506006"
          ],
          "isEmpty": 0,
          "isCommentOut": 0
        },
        {
          "rowIndex": 22,
          "strings": [
            "Character",
            "洛贝拉SSR",
            "Tender,0",
            "中"
          ],
          "isEmpty": 0,
          "isCommentOut": 0
        },
        {
          "rowIndex": 23,
          "strings": [
            "Text",
            "426",
            "洛贝拉SSR",
            "",
            "",
            "",
            "",
            "",
            "",
            "",
            "504506007"
          ],
          "isEmpty": 0,
          "isCommentOut": 0
        },
        {
          "rowIndex": 24,
          "strings": [
            "Character",
            "洛贝拉SSR",
            "Tender,0",
            "中"
          ],
          "isEmpty": 0,
          "isCommentOut": 0
        },
        {
          "rowIndex": 25,
          "strings": [
            "Text",
            "426",
            "洛贝拉SSR",
            "",
            "",
            "",
            "",
            "",
            "",
            "",
            "504506008"
          ],
          "isEmpty": 0,
          "isCommentOut": 0
        },
        {
          "rowIndex": 26,
          "strings": [
            "ChangeMessageWindow",
            "AVGNarrator",
            "",
            "",
            "",
            "",
            "",
            "",
            "",
            "",
            "",
            "",
            "",
            "",
            "",
            "",
            "",
            "",
            ""
          ],
          "isEmpty": 0,
          "isCommentOut": 0
        },
        {
          "rowIndex": 27,
          "strings": [
            "CharacterOff",
            "洛贝拉SSR",
            "",
            "",
            "",
            "",
            "",
            "",
            "",
            "",
            "",
            "",
            "",
            "",
            "",
            "",
            "",
            "",
            ""
          ],
          "isEmpty": 0,
          "isCommentOut": 0
        },
        {
          "rowIndex": 28,
          "strings": [
            "Se",
            "2010158",
            "False",
            "1",
            "",
            "0",
            "0",
            "",
            "",
            "",
            "",
            "",
            "",
            "",
            "",
            "",
            "",
            "",
            ""
          ],
          "isEmpty": 0,
          "isCommentOut": 0
        },
        {
          "rowIndex": 29,
          "strings": [
            "Text",
            "",
            "",
            "",
            "",
            "",
            "",
            "",
            "",
            "",
            "504506009"
          ],
          "isEmpty": 0,
          "isCommentOut": 0
        },
        {
          "rowIndex": 30,
          "strings": [
            "ChangeMessageWindow",
            "AVGWindow",
            "",
            "",
            "",
            "",
            "",
            "",
            "",
            "",
            "",
            "",
            "",
            "",
            "",
            "",
            "",
            "",
            ""
          ],
          "isEmpty": 0,
          "isCommentOut": 0
        },
        {
          "rowIndex": 31,
          "strings": [
            "Text",
            "50",
            "",
            "",
            "",
            "",
            "",
            "",
            "",
            "",
            "504506010"
          ],
          "isEmpty": 0,
          "isCommentOut": 0
        },
        {
          "rowIndex": 32,
          "strings": [
            "ChangeMessageWindow",
            "AVGNarrator",
            "",
            "",
            "",
            "",
            "",
            "",
            "",
            "",
            "",
            "",
            "",
            "",
            "",
            "",
            "",
            "",
            ""
          ],
          "isEmpty": 0,
          "isCommentOut": 0
        },
        {
          "rowIndex": 33,
          "strings": [
            "Text",
            "",
            "",
            "",
            "",
            "",
            "",
            "",
            "",
            "",
            "504506011"
          ],
          "isEmpty": 0,
          "isCommentOut": 0
        },
        {
          "rowIndex": 34,
          "strings": [
            "Text",
            "",
            "",
            "",
            "",
            "",
            "",
            "",
            "",
            "",
            "504506012"
          ],
          "isEmpty": 0,
          "isCommentOut": 0
        },
        {
          "rowIndex": 35,
          "strings": [
            "ChangeMessageWindow",
            "AVGWindow",
            "",
            "",
            "",
            "",
            "",
            "",
            "",
            "",
            "",
            "",
            "",
            "",
            "",
            "",
            "",
            "",
            ""
          ],
          "isEmpty": 0,
          "isCommentOut": 0
        },
        {
          "rowIndex": 36,
          "strings": [
            "Text",
            "50",
            "",
            "",
            "",
            "",
            "",
            "",
            "",
            "",
            "504506013"
          ],
          "isEmpty": 0,
          "isCommentOut": 0
        },
        {
          "rowIndex": 37,
          "strings": [
            "Character",
            "洛贝拉SSR",
            "Tender,0",
            "中"
          ],
          "isEmpty": 0,
          "isCommentOut": 0
        },
        {
          "rowIndex": 38,
          "strings": [
            "Text",
            "426",
            "洛贝拉SSR",
            "",
            "",
            "",
            "",
            "",
            "",
            "",
            "504506014"
          ],
          "isEmpty": 0,
          "isCommentOut": 0
        },
        {
          "rowIndex": 39,
          "strings": [
            "ChangeMessageWindow",
            "AVGNarrator",
            "",
            "",
            "",
            "",
            "",
            "",
            "",
            "",
            "",
            "",
            "",
            "",
            "",
            "",
            "",
            "",
            ""
          ],
          "isEmpty": 0,
          "isCommentOut": 0
        },
        {
          "rowIndex": 40,
          "strings": [
            "CharacterOff",
            "洛贝拉SSR",
            "",
            "",
            "",
            "",
            "",
            "",
            "",
            "",
            "",
            "",
            "",
            "",
            "",
            "",
            "",
            "",
            ""
          ],
          "isEmpty": 0,
          "isCommentOut": 0
        },
        {
          "rowIndex": 41,
          "strings": [
            "Se",
            "2010135",
            "False",
            "1",
            "",
            "0",
            "0",
            "",
            "",
            "",
            "",
            "",
            "",
            "",
            "",
            "",
            "",
            "",
            ""
          ],
          "isEmpty": 0,
          "isCommentOut": 0
        },
        {
          "rowIndex": 42,
          "strings": [
            "Text",
            "",
            "",
            "",
            "",
            "",
            "",
            "",
            "",
            "",
            "504506015"
          ],
          "isEmpty": 0,
          "isCommentOut": 0
        },
        {
          "rowIndex": 43,
          "strings": [
            "ChangeMessageWindow",
            "AVGWindow",
            "",
            "",
            "",
            "",
            "",
            "",
            "",
            "",
            "",
            "",
            "",
            "",
            "",
            "",
            "",
            "",
            ""
          ],
          "isEmpty": 0,
          "isCommentOut": 0
        },
        {
          "rowIndex": 44,
          "strings": [
            "Text",
            "50",
            "",
            "",
            "",
            "",
            "",
            "",
            "",
            "",
            "504506016"
          ],
          "isEmpty": 0,
          "isCommentOut": 0
        },
        {
          "rowIndex": 45,
          "strings": [
            "ChangeMessageWindow",
            "AVGNarrator",
            "",
            "",
            "",
            "",
            "",
            "",
            "",
            "",
            "",
            "",
            "",
            "",
            "",
            "",
            "",
            "",
            ""
          ],
          "isEmpty": 0,
          "isCommentOut": 0
        },
        {
          "rowIndex": 46,
          "strings": [
            "Character",
            "洛贝拉SSR",
            "Nervous,0",
            "中"
          ],
          "isEmpty": 0,
          "isCommentOut": 0
        },
        {
          "rowIndex": 47,
          "strings": [
            "Se",
            "2010158",
            "False",
            "1",
            "",
            "0",
            "0",
            "",
            "",
            "",
            "",
            "",
            "",
            "",
            "",
            "",
            "",
            "",
            ""
          ],
          "isEmpty": 0,
          "isCommentOut": 0
        },
        {
          "rowIndex": 48,
          "strings": [
            "Text",
            "",
            "",
            "",
            "",
            "",
            "",
            "",
            "",
            "",
            "504506017"
          ],
          "isEmpty": 0,
          "isCommentOut": 0
        },
        {
          "rowIndex": 49,
          "strings": [
            "ChangeMessageWindow",
            "AVGWindow",
            "",
            "",
            "",
            "",
            "",
            "",
            "",
            "",
            "",
            "",
            "",
            "",
            "",
            "",
            "",
            "",
            ""
          ],
          "isEmpty": 0,
          "isCommentOut": 0
        },
        {
          "rowIndex": 50,
          "strings": [
            "Character",
            "洛贝拉SSR",
            "Nervous,0",
            "中"
          ],
          "isEmpty": 0,
          "isCommentOut": 0
        },
        {
          "rowIndex": 51,
          "strings": [
            "Text",
            "426",
            "洛贝拉SSR",
            "",
            "",
            "",
            "",
            "",
            "",
            "",
            "504506018"
          ],
          "isEmpty": 0,
          "isCommentOut": 0
        },
        {
          "rowIndex": 52,
          "strings": [
            "ChangeMessageWindow",
            "AVGNarrator",
            "",
            "",
            "",
            "",
            "",
            "",
            "",
            "",
            "",
            "",
            "",
            "",
            "",
            "",
            "",
            "",
            ""
          ],
          "isEmpty": 0,
          "isCommentOut": 0
        },
        {
          "rowIndex": 53,
          "strings": [
            "Character",
            "洛贝拉SSR",
            "Nervous,0",
            "中"
          ],
          "isEmpty": 0,
          "isCommentOut": 0
        },
        {
          "rowIndex": 54,
          "strings": [
            "Se",
            "2010163",
            "False",
            "1",
            "",
            "0",
            "0",
            "",
            "",
            "",
            "",
            "",
            "",
            "",
            "",
            "",
            "",
            "",
            ""
          ],
          "isEmpty": 0,
          "isCommentOut": 0
        },
        {
          "rowIndex": 55,
          "strings": [
            "Text",
            "",
            "",
            "",
            "",
            "",
            "",
            "",
            "",
            "",
            "504506019"
          ],
          "isEmpty": 0,
          "isCommentOut": 0
        },
        {
          "rowIndex": 56,
          "strings": [
            "ChangeMessageWindow",
            "AVGWindow",
            "",
            "",
            "",
            "",
            "",
            "",
            "",
            "",
            "",
            "",
            "",
            "",
            "",
            "",
            "",
            "",
            ""
          ],
          "isEmpty": 0,
          "isCommentOut": 0
        },
        {
          "rowIndex": 57,
          "strings": [
            "Character",
            "洛贝拉SSR",
            "Nervous,0|Surprised,0.5",
            "中"
          ],
          "isEmpty": 0,
          "isCommentOut": 0
        },
        {
          "rowIndex": 58,
          "strings": [
            "Text",
            "50",
            "",
            "",
            "",
            "",
            "",
            "",
            "",
            "",
            "504506020"
          ],
          "isEmpty": 0,
          "isCommentOut": 0
        },
        {
          "rowIndex": 59,
          "strings": [
            "Character",
            "洛贝拉SSR",
            "Surprised,0|Tender,0.5",
            "中"
          ],
          "isEmpty": 0,
          "isCommentOut": 0
        },
        {
          "rowIndex": 60,
          "strings": [
            "Text",
            "426",
            "洛贝拉SSR",
            "",
            "",
            "",
            "",
            "",
            "",
            "",
            "504506021"
          ],
          "isEmpty": 0,
          "isCommentOut": 0
        },
        {
          "rowIndex": 61,
          "strings": [
            "Character",
            "洛贝拉SSR",
            "Tender,0",
            "中"
          ],
          "isEmpty": 0,
          "isCommentOut": 0
        },
        {
          "rowIndex": 62,
          "strings": [
            "Text",
            "50",
            "",
            "",
            "",
            "",
            "",
            "",
            "",
            "",
            "504506022"
          ],
          "isEmpty": 0,
          "isCommentOut": 0
        },
        {
          "rowIndex": 63,
          "strings": [
            "Character",
            "洛贝拉SSR",
            "Tender,0|Surprised,0.5",
            "中"
          ],
          "isEmpty": 0,
          "isCommentOut": 0
        },
        {
          "rowIndex": 64,
          "strings": [
            "Text",
            "426",
            "洛贝拉SSR",
            "",
            "",
            "",
            "",
            "",
            "",
            "",
            "504506023"
          ],
          "isEmpty": 0,
          "isCommentOut": 0
        },
        {
          "rowIndex": 65,
          "strings": [
            "ChangeMessageWindow",
            "AVGNarrator",
            "",
            "",
            "",
            "",
            "",
            "",
            "",
            "",
            "",
            "",
            "",
            "",
            "",
            "",
            "",
            "",
            ""
          ],
          "isEmpty": 0,
          "isCommentOut": 0
        },
        {
          "rowIndex": 66,
          "strings": [
            "CharacterOff",
            "洛贝拉SSR",
            "",
            "",
            "",
            "",
            "",
            "",
            "",
            "",
            "",
            "",
            "",
            "",
            "",
            "",
            "",
            "",
            ""
          ],
          "isEmpty": 0,
          "isCommentOut": 0
        },
        {
          "rowIndex": 67,
          "strings": [
            "Se",
            "2010135",
            "False",
            "1",
            "",
            "0",
            "0",
            "",
            "",
            "",
            "",
            "",
            "",
            "",
            "",
            "",
            "",
            "",
            ""
          ],
          "isEmpty": 0,
          "isCommentOut": 0
        },
        {
          "rowIndex": 68,
          "strings": [
            "Text",
            "",
            "",
            "",
            "",
            "",
            "",
            "",
            "",
            "",
            "504506024"
          ],
          "isEmpty": 0,
          "isCommentOut": 0
        },
        {
          "rowIndex": 69,
          "strings": [
            "ChangeMessageWindow",
            "AVGWindow",
            "",
            "",
            "",
            "",
            "",
            "",
            "",
            "",
            "",
            "",
            "",
            "",
            "",
            "",
            "",
            "",
            ""
          ],
          "isEmpty": 0,
          "isCommentOut": 0
        },
        {
          "rowIndex": 70,
          "strings": [
            "Text",
            "50",
            "",
            "",
            "",
            "",
            "",
            "",
            "",
            "",
            "504506025"
          ],
          "isEmpty": 0,
          "isCommentOut": 0
        },
        {
          "rowIndex": 71,
          "strings": [
            "Text",
            "50",
            "",
            "",
            "",
            "",
            "",
            "",
            "",
            "",
            "504506026"
          ],
          "isEmpty": 0,
          "isCommentOut": 0
        },
        {
          "rowIndex": 72,
          "strings": [
            "Character",
            "洛贝拉SSR",
            "Nervous,0",
            "中"
          ],
          "isEmpty": 0,
          "isCommentOut": 0
        },
        {
          "rowIndex": 73,
          "strings": [
            "Text",
            "426",
            "洛贝拉SSR",
            "",
            "",
            "",
            "",
            "",
            "",
            "",
            "504506027"
          ],
          "isEmpty": 0,
          "isCommentOut": 0
        },
        {
          "rowIndex": 74,
          "strings": [
            "Character",
            "洛贝拉SSR",
            "Nervous,0|Surprised,0.5",
            "中"
          ],
          "isEmpty": 0,
          "isCommentOut": 0
        },
        {
          "rowIndex": 75,
          "strings": [
            "Text",
            "426",
            "洛贝拉SSR",
            "",
            "",
            "",
            "",
            "",
            "",
            "",
            "504506028"
          ],
          "isEmpty": 0,
          "isCommentOut": 0
        },
        {
          "rowIndex": 76,
          "strings": [
            "Character",
            "洛贝拉SSR",
            "Surprised,0|Worried,0.5",
            "中"
          ],
          "isEmpty": 0,
          "isCommentOut": 0
        },
        {
          "rowIndex": 77,
          "strings": [
            "Text",
            "426",
            "洛贝拉SSR",
            "",
            "",
            "",
            "",
            "",
            "",
            "",
            "504506029"
          ],
          "isEmpty": 0,
          "isCommentOut": 0
        },
        {
          "rowIndex": 78,
          "strings": [
            "ChangeMessageWindow",
            "AVGNarrator",
            "",
            "",
            "",
            "",
            "",
            "",
            "",
            "",
            "",
            "",
            "",
            "",
            "",
            "",
            "",
            "",
            ""
          ],
          "isEmpty": 0,
          "isCommentOut": 0
        },
        {
          "rowIndex": 79,
          "strings": [
            "Character",
            "洛贝拉SSR",
            "Worried,0",
            "中"
          ],
          "isEmpty": 0,
          "isCommentOut": 0
        },
        {
          "rowIndex": 80,
          "strings": [
            "Text",
            "",
            "",
            "",
            "",
            "",
            "",
            "",
            "",
            "",
            "504506030"
          ],
          "isEmpty": 0,
          "isCommentOut": 0
        },
        {
          "rowIndex": 81,
          "strings": [
            "ChangeMessageWindow",
            "AVGWindow",
            "",
            "",
            "",
            "",
            "",
            "",
            "",
            "",
            "",
            "",
            "",
            "",
            "",
            "",
            "",
            "",
            ""
          ],
          "isEmpty": 0,
          "isCommentOut": 0
        },
        {
          "rowIndex": 82,
          "strings": [
            "Character",
            "洛贝拉SSR",
            "Worried,0|Surprised,0.5",
            "中"
          ],
          "isEmpty": 0,
          "isCommentOut": 0
        },
        {
          "rowIndex": 83,
          "strings": [
            "Text",
            "50",
            "",
            "",
            "",
            "",
            "",
            "",
            "",
            "",
            "504506031"
          ],
          "isEmpty": 0,
          "isCommentOut": 0
        },
        {
          "rowIndex": 84,
          "strings": [
            "ChangeMessageWindow",
            "AVGNarrator",
            "",
            "",
            "",
            "",
            "",
            "",
            "",
            "",
            "",
            "",
            "",
            "",
            "",
            "",
            "",
            "",
            ""
          ],
          "isEmpty": 0,
          "isCommentOut": 0
        },
        {
          "rowIndex": 85,
          "strings": [
            "CharacterOff",
            "洛贝拉SSR",
            "",
            "",
            "",
            "",
            "",
            "",
            "",
            "",
            "",
            "",
            "",
            "",
            "",
            "",
            "",
            "",
            ""
          ],
          "isEmpty": 0,
          "isCommentOut": 0
        },
        {
          "rowIndex": 86,
          "strings": [
            "Se",
            "2010158",
            "False",
            "1",
            "",
            "0",
            "0",
            "",
            "",
            "",
            "",
            "",
            "",
            "",
            "",
            "",
            "",
            "",
            ""
          ],
          "isEmpty": 0,
          "isCommentOut": 0
        },
        {
          "rowIndex": 87,
          "strings": [
            "Text",
            "",
            "",
            "",
            "",
            "",
            "",
            "",
            "",
            "",
            "504506032"
          ],
          "isEmpty": 0,
          "isCommentOut": 0
        },
        {
          "rowIndex": 88,
          "strings": [
            "Se",
            "2010135",
            "False",
            "1",
            "",
            "0",
            "0",
            "",
            "",
            "",
            "",
            "",
            "",
            "",
            "",
            "",
            "",
            "",
            ""
          ],
          "isEmpty": 0,
          "isCommentOut": 0
        },
        {
          "rowIndex": 89,
          "strings": [
            "Text",
            "",
            "",
            "",
            "",
            "",
            "",
            "",
            "",
            "",
            "504506033"
          ],
          "isEmpty": 0,
          "isCommentOut": 0
        },
        {
          "rowIndex": 90,
          "strings": [
            "ChangeMessageWindow",
            "AVGWindow",
            "",
            "",
            "",
            "",
            "",
            "",
            "",
            "",
            "",
            "",
            "",
            "",
            "",
            "",
            "",
            "",
            ""
          ],
          "isEmpty": 0,
          "isCommentOut": 0
        },
        {
          "rowIndex": 91,
          "strings": [
            "Text",
            "50",
            "",
            "",
            "",
            "",
            "",
            "",
            "",
            "",
            "504506034"
          ],
          "isEmpty": 0,
          "isCommentOut": 0
        },
        {
          "rowIndex": 92,
          "strings": [
            "Character",
            "洛贝拉SSR",
            "Surprised,0",
            "中"
          ],
          "isEmpty": 0,
          "isCommentOut": 0
        },
        {
          "rowIndex": 93,
          "strings": [
            "Tween",
            "洛贝拉SSR",
            "ShakePosition",
            "time=1 delay=0 x=10 y=0 start=0",
            "",
            "loop=1",
            "",
            "",
            "",
            "NoWait",
            "",
            "",
            "",
            "",
            "",
            "",
            "",
            "",
            ""
          ],
          "isEmpty": 0,
          "isCommentOut": 0
        },
        {
          "rowIndex": 94,
          "strings": [
            "Text",
            "426",
            "洛贝拉SSR",
            "",
            "",
            "",
            "",
            "",
            "",
            "",
            "504506035"
          ],
          "isEmpty": 0,
          "isCommentOut": 0
        },
        {
          "rowIndex": 95,
          "strings": [
            "Character",
            "洛贝拉SSR",
            "Surprised,0",
            "中"
          ],
          "isEmpty": 0,
          "isCommentOut": 0
        },
        {
          "rowIndex": 96,
          "strings": [
            "Text",
            "50",
            "",
            "",
            "",
            "",
            "",
            "",
            "",
            "",
            "504506036"
          ],
          "isEmpty": 0,
          "isCommentOut": 0
        },
        {
          "rowIndex": 97,
          "strings": [
            "Character",
            "洛贝拉SSR",
            "Surprised,0",
            "中"
          ],
          "isEmpty": 0,
          "isCommentOut": 0
        },
        {
          "rowIndex": 98,
          "strings": [
            "Param",
            "fuzhu1=(4+1)",
            "",
            "",
            "",
            "",
            "",
            "",
            "",
            "",
            "",
            "",
            "",
            "",
            "",
            "",
            "",
            "",
            ""
          ],
          "isEmpty": 0,
          "isCommentOut": 0
        },
        {
          "rowIndex": 99,
          "strings": [
            "BgOff",
            "",
            "",
            "",
            "",
            "",
            "2",
            "0",
            "",
            "",
            "",
            "",
            "",
            "",
            "",
            "",
            "",
            "",
            ""
          ],
          "isEmpty": 0,
          "isCommentOut": 0
        },
        {
          "rowIndex": 100,
          "strings": [
            "CharacterOff",
            "",
            "",
            "",
            "",
            "",
            "2",
            "4",
            "",
            "",
            "",
            "",
            "",
            "",
            "",
            "",
            "",
            "",
            ""
          ],
          "isEmpty": 0,
          "isCommentOut": 0
        },
        {
          "rowIndex": 101,
          "strings": [
            "StopBgm",
            "",
            "",
            "",
            "",
            "",
            "2",
            "4",
            "",
            "",
            "",
            "",
            "",
            "",
            "",
            "",
            "",
            "",
            ""
          ],
          "isEmpty": 0,
          "isCommentOut": 0
        },
        {
          "rowIndex": 102,
          "strings": [
            "StopSe",
            "",
            "",
            "",
            "",
            "",
            "2",
            "0",
            "",
            "",
            "",
            "",
            "",
            "",
            "",
            "",
            "",
            "",
            ""
          ],
          "isEmpty": 0,
          "isCommentOut": 0
        },
        {
          "rowIndex": 103,
          "strings": [
            "Text",
            "426",
            "洛贝拉SSR",
            "",
            "",
            "",
            "Next",
            "",
            "",
            "",
            "504506037"
          ],
          "isEmpty": 0,
          "isCommentOut": 0
        },
        {
          "rowIndex": 104,
          "strings": [
            "EndScenario"
          ],
          "isEmpty": 0,
          "isCommentOut": 0
        }
      ],
      "name": "Assets/Utage/BuildResources/NewAVG_Ties/Ties045/T04506.xls:T04506",
      "type": 1,
      "textLength": 2490,
      "headerRow": 0,
      "entityIndexTbl": [
        99,
        102
      ],
      "entityDataList": [
        {
          "originalStrings": [
            "BgOff",
            "",
            "",
            "",
            "",
            "",
            "2",
            "&fuzhu1",
            "",
            "",
            "",
            "",
            "",
            "",
            "",
            "",
            "",
            "",
            ""
          ]
        },
        {
          "originalStrings": [
            "StopSe",
            "",
            "",
            "",
            "",
            "",
            "2",
            "&fuzhu1",
            "",
            "",
            "",
            "",
            "",
            "",
            "",
            "",
            "",
            "",
            ""
          ]
        }
      ]
    }
  ]
}